odoo/addons/partner_identification_import/README.rst
odoo/addons/partner_identification_import/__init__.py
odoo/addons/partner_identification_import/__manifest__.py
odoo/addons/partner_identification_import/i18n/es.po
odoo/addons/partner_identification_import/i18n/it.po
odoo/addons/partner_identification_import/i18n/partner_identification_import.pot
odoo/addons/partner_identification_import/models/__init__.py
odoo/addons/partner_identification_import/models/business_document_import.py
odoo/addons/partner_identification_import/readme/CONTRIBUTORS.md
odoo/addons/partner_identification_import/readme/CREDITS.md
odoo/addons/partner_identification_import/readme/DESCRIPTION.md
odoo/addons/partner_identification_import/static/description/icon.png
odoo/addons/partner_identification_import/static/description/index.html
odoo/addons/partner_identification_import/tests/__init__.py
odoo/addons/partner_identification_import/tests/test_business_document_import.py
odoo_addon_partner_identification_import-18.0.1.0.0.4.dist-info/METADATA
odoo_addon_partner_identification_import-18.0.1.0.0.4.dist-info/WHEEL
odoo_addon_partner_identification_import-18.0.1.0.0.4.dist-info/top_level.txt
odoo_addon_partner_identification_import-18.0.1.0.0.4.dist-info/RECORD
