Metadata-Version: 2.1
Name: odoo-addon-partner_identification_import
Version: 18.0.1.0.0.4
Requires-Python: >=3.10
Requires-Dist: odoo-addon-base_business_document_import==18.0.*
Requires-Dist: odoo-addon-partner_identification==18.0.*
Requires-Dist: odoo==18.0.*
Summary: Provides partner matching on extra ID
Home-page: https://github.com/OCA/edi
License: AGPL-3
Author: BCIM, Odoo Community Association (OCA)
Author-email: support@odoo-community.org
Classifier: Programming Language :: Python
Classifier: Framework :: Odoo
Classifier: Framework :: Odoo :: 18.0
Classifier: License :: OSI Approved :: GNU Affero General Public License v3
